webcolors-24.11.0.dist-info/METADATA
webcolors-24.11.0.dist-info/WHEEL
webcolors-24.11.0.dist-info/entry_points.txt
webcolors-24.11.0.dist-info/licenses/LICENSE
webcolors/__init__.py
webcolors/_conversion.py
webcolors/_definitions.py
webcolors/_html5.py
webcolors/_normalization.py
webcolors/_types.py
webcolors-24.11.0.dist-info/RECORD
