Metadata-Version: 2.1
Name: webcolors
Version: 24.11.0
Summary: A library for working with the color formats defined by HTML and CSS.
Keywords: color,css,html,web
Author: James Bennett
License: BSD-3-Clause
Classifier: Development Status :: 5 - Production/Stable
Classifier: Environment :: Web Environment
Classifier: Intended Audience :: Developers
Classifier: License :: OSI Approved :: BSD License
Classifier: Operating System :: OS Independent
Classifier: Programming Language :: Python
Classifier: Programming Language :: Python :: 3
Classifier: Programming Language :: Python :: 3.9
Classifier: Programming Language :: Python :: 3.10
Classifier: Programming Language :: Python :: 3.11
Classifier: Programming Language :: Python :: 3.12
Classifier: Programming Language :: Python :: 3.13
Classifier: Topic :: Utilities
Project-URL: Documentation, https://webcolors.readthedocs.io
Project-URL: Source Code, https://github.com/ubernostrum/webcolors
Requires-Python: >=3.9
